{
	"info": {
		"_postman_id": "039bd5b9-210d-4702-b66c-9b62cbf7ddf6",
		"name": "Users",
		"schema": "https://schema.getpostman.com/json/collection/v2.1.0/collection.json"
	},
	"item": [
		{
			"name": "Get Users",
			"request": {
				"auth": {
					"type": "bearer",
					"bearer": [
						{
							"key": "token",
							"value": "eyJhbGciOiJIUzI1NiIsInR5cCI6IkpXVCJ9.eyJpZCI6MTAwMCwiZW1haWwiOiJhbmdlbGluLmNhbHVAZ21haWwuY29tIiwiaWF0IjoxNjA0NDc3NDQ1LCJleHAiOjE2MDQ1NjM4NDV9.op0au6y2izOI1rgYpAcE3m0KDhrbvDQT4vU08mM_J4E",
							"type": "string"
						}
					]
				},
				"method": "GET",
				"header": [],
				"url": {
					"raw": "http://localhost:5000/api/users",
					"protocol": "http",
					"host": [
						"localhost"
					],
					"port": "5000",
					"path": [
						"api",
						"users"
					]
				}
			},
			"response": []
		},
		{
			"name": "Get Single User",
			"request": {
				"auth": {
					"type": "bearer",
					"bearer": [
						{
							"key": "token",
							"value": "eyJhbGciOiJIUzI1NiIsInR5cCI6IkpXVCJ9.eyJpZCI6MTAwMCwiZW1haWwiOiJhbmdlbGluLmNhbHVAZ21haWwuY29tIiwiaWF0IjoxNjA0NDc3NDQ1LCJleHAiOjE2MDQ1NjM4NDV9.op0au6y2izOI1rgYpAcE3m0KDhrbvDQT4vU08mM_J4E",
							"type": "string"
						}
					]
				},
				"method": "GET",
				"header": [],
				"url": {
					"raw": "http://localhost:5000/api/users/1",
					"protocol": "http",
					"host": [
						"localhost"
					],
					"port": "5000",
					"path": [
						"api",
						"users",
						"1"
					]
				}
			},
			"response": []
		},
		{
			"name": "Get a list of all orders",
			"request": {
				"auth": {
					"type": "bearer",
					"bearer": [
						{
							"key": "token",
							"value": "eyJhbGciOiJIUzI1NiIsInR5cCI6IkpXVCJ9.eyJpZCI6MTAwMCwiZW1haWwiOiJhbmdlbGluLmNhbHVAZ21haWwuY29tIiwiaWF0IjoxNjA0NDc3NDQ1LCJleHAiOjE2MDQ1NjM4NDV9.op0au6y2izOI1rgYpAcE3m0KDhrbvDQT4vU08mM_J4E",
							"type": "string"
						}
					]
				},
				"method": "GET",
				"header": [],
				"url": {
					"raw": "http://localhost:5000/api/users/1/orders",
					"protocol": "http",
					"host": [
						"localhost"
					],
					"port": "5000",
					"path": [
						"api",
						"users",
						"1",
						"orders"
					]
				}
			},
			"response": []
		},
		{
			"name": "Edit User",
			"request": {
				"auth": {
					"type": "bearer",
					"bearer": [
						{
							"key": "token",
							"value": "eyJhbGciOiJIUzI1NiIsInR5cCI6IkpXVCJ9.eyJpZCI6MTAwMCwiZW1haWwiOiJhbmdlbGluLmNhbHVAZ21haWwuY29tIiwiaWF0IjoxNjA0NDc3NDQ1LCJleHAiOjE2MDQ1NjM4NDV9.op0au6y2izOI1rgYpAcE3m0KDhrbvDQT4vU08mM_J4E",
							"type": "string"
						}
					]
				},
				"method": "PATCH",
				"header": [],
				"url": {
					"raw": "http://localhost:5000/api/users/1",
					"protocol": "http",
					"host": [
						"localhost"
					],
					"port": "5000",
					"path": [
						"api",
						"users",
						"1"
					]
				}
			},
			"response": []
		}
	],
	"protocolProfileBehavior": {}
}